{"GlobalPropertiesHash":"0l52Q3F3Y6KyyxKN3Xd91kKLw2Yn8OzKDjRk96YtRz8=","FingerprintPatternsHash":"gq3WsqcKBUGTSNle7RKKyXRIwh7M8ccEqOqYvIzoM04=","PropertyOverridesHash":"8ZRc1sGeVrPBx4lD717BgRaQekyh78QKV9SKsdt638U=","InputHashes":["leRRlPeEyxjtb1UrdO/s/j4lD654Gk8wyz0RurYMNvU=","fiwHpYDkY0MrWzRmoQ4tVJmGOKQ14d7Sx8uCGV5AEX8=","uRlE2vmk5x5dytz1Hct0YYWbwBUi7iyY0UhHuijKBZs="],"CachedAssets":{"leRRlPeEyxjtb1UrdO/s/j4lD654Gk8wyz0RurYMNvU=":{"Identity":"/Users/wow/Documents/todo app/wwwroot/index.html","SourceId":"TodoApp","SourceType":"Discovered","ContentRoot":"/Users/wow/Documents/todo app/wwwroot/","BasePath":"_content/TodoApp","RelativePath":"index#[.{fingerprint}]?.html","AssetKind":"All","AssetMode":"All","AssetRole":"Primary","AssetMergeBehavior":null,"AssetMergeSource":"","RelatedAsset":null,"AssetTraitName":null,"AssetTraitValue":null,"Fingerprint":"yerrhauhv6","Integrity":"ivxuHNtpPsBTJggbEboWXRaODBoqoyO1b0j2rrIDgBE=","CopyToOutputDirectory":"Never","CopyToPublishDirectory":"PreserveNewest","OriginalItemSpec":"wwwroot/index.html","FileLength":3469,"LastWriteTime":"2025-08-25T08:35:50.521373+00:00"},"fiwHpYDkY0MrWzRmoQ4tVJmGOKQ14d7Sx8uCGV5AEX8=":{"Identity":"/Users/wow/Documents/todo app/wwwroot/script.js","SourceId":"TodoApp","SourceType":"Discovered","ContentRoot":"/Users/wow/Documents/todo app/wwwroot/","BasePath":"_content/TodoApp","RelativePath":"script#[.{fingerprint}]?.js","AssetKind":"All","AssetMode":"All","AssetRole":"Primary","AssetMergeBehavior":null,"AssetMergeSource":"","RelatedAsset":null,"AssetTraitName":null,"AssetTraitValue":null,"Fingerprint":"jsboy3w0yb","Integrity":"TWDndDTxr6/NV7NhcCb6WmNS1VEGiUk\u002BxuwiPDDEIDA=","CopyToOutputDirectory":"Never","CopyToPublishDirectory":"PreserveNewest","OriginalItemSpec":"wwwroot/script.js","FileLength":6306,"LastWriteTime":"2025-08-25T17:25:04.9584029+00:00"},"uRlE2vmk5x5dytz1Hct0YYWbwBUi7iyY0UhHuijKBZs=":{"Identity":"/Users/wow/Documents/todo app/wwwroot/styles.css","SourceId":"TodoApp","SourceType":"Discovered","ContentRoot":"/Users/wow/Documents/todo app/wwwroot/","BasePath":"_content/TodoApp","RelativePath":"styles#[.{fingerprint}]?.css","AssetKind":"All","AssetMode":"All","AssetRole":"Primary","AssetMergeBehavior":null,"AssetMergeSource":"","RelatedAsset":null,"AssetTraitName":null,"AssetTraitValue":null,"Fingerprint":"zs6z5dqdby","Integrity":"M2aHpKJhny888rHYe/o8VKUkPyMJx71iFcubuuLI9hU=","CopyToOutputDirectory":"Never","CopyToPublishDirectory":"PreserveNewest","OriginalItemSpec":"wwwroot/styles.css","FileLength":5240,"LastWriteTime":"2025-08-25T17:25:04.9602624+00:00"}},"CachedCopyCandidates":{}}